<annotation>
	<folder>JPEGImages</folder>
	<filename>cat.68.jpg</filename>
	<path>D:\python\train_keras_yolov3\labelImg-master\VOC2007\JPEGImages\cat.68.jpg</path>
	<source>
		<database>Unknown</database>
	</source>
	<size>
		<width>249</width>
		<height>181</height>
		<depth>3</depth>
	</size>
	<segmented>0</segmented>
	<object>
		<name>cat</name>
		<pose>Unspecified</pose>
		<truncated>1</truncated>
		<difficult>0</difficult>
		<bndbox>
			<xmin>1</xmin>
			<ymin>11</ymin>
			<xmax>240</xmax>
			<ymax>172</ymax>
		</bndbox>
	</object>
</annotation>
